pycommon/__init__.py
pycommon/caseinsensitivedict.py
pycommon/dynamo.py
pycommon/path.py
pycommon_andreacioni-0.0.4.dist-info/METADATA
pycommon_andreacioni-0.0.4.dist-info/RECORD
pycommon_andreacioni-0.0.4.dist-info/WHEEL
pycommon_andreacioni-0.0.4.dist-info/top_level.txt
