Metadata-Version: 2.1
Name: pycommon-andreacioni
Version: 0.0.4
Summary: Common utility classes from some Python projects
Home-page: https://github.com/andreacioni/pycommon
Author: Andrea Cioni
License: UNKNOWN
Platform: UNKNOWN
Classifier: Programming Language :: Python :: 3
Classifier: License :: OSI Approved :: MIT License
Classifier: Operating System :: OS Independent
